ml_algorithms/__init__.py
ml_algorithms/main.py
ml_algorithms-0.2.0.dist-info/METADATA
ml_algorithms-0.2.0.dist-info/WHEEL
ml_algorithms-0.2.0.dist-info/top_level.txt
ml_algorithms-0.2.0.dist-info/RECORD
